speech_intelligibility_index/BUILD.bazel
speech_intelligibility_index/WORKSPACE
speech_intelligibility_index/__init__.py
speech_intelligibility_index/sii.py
speech_intelligibility_index/sii_jax.py
speech_intelligibility_index/sii_jax_test.py
speech_intelligibility_index/sii_test.py
speech_intelligibility_index-1.0.2.dist-info/METADATA
speech_intelligibility_index-1.0.2.dist-info/WHEEL
speech_intelligibility_index-1.0.2.dist-info/licenses/LICENSE
speech_intelligibility_index-1.0.2.dist-info/RECORD
