Metadata-Version: 2.1
Name: speech-intelligibility-index
Version: 1.0.2
Summary: Speech Intelligibility Index
Project-URL: Homepage, https://github.com/google/speech_intelligibility_index
Project-URL: Bug Tracker, https://github.com/google/speech_intelligibility_index/issues
Author-email: Malcolm Slaney <speech-intelligibility-index-maintainers@googlegroups.com>
License-Expression: Apache-2.0
License-File: LICENSE
Classifier: License :: OSI Approved :: Apache Software License
Classifier: Operating System :: OS Independent
Classifier: Programming Language :: Python :: 3
Requires-Python: >=3.6
Requires-Dist: absl-py
Requires-Dist: jax
Requires-Dist: jaxlib
Requires-Dist: matplotlib
Requires-Dist: numpy
